ccl_localstoragerss.py
ccl_localstoragerss-1.1.3.dist-info/LICENSE
ccl_localstoragerss-1.1.3.dist-info/METADATA
ccl_localstoragerss-1.1.3.dist-info/WHEEL
ccl_localstoragerss-1.1.3.dist-info/RECORD
